pre_commit_rs/__init__.py
pre_commit_rs/__main__.py
pre_commit_rs-0.0.0.dist-info/LICENSE
pre_commit_rs-0.0.0.dist-info/METADATA
pre_commit_rs-0.0.0.dist-info/WHEEL
pre_commit_rs-0.0.0.dist-info/asottile_cfgv
pre_commit_rs-0.0.0.dist-info/pre-commit_pre-commit
pre_commit_rs-0.0.0.dist-info/top_level.txt
pre_commit_rs-0.0.0.dist-info/RECORD
