Metadata-Version: 2.1
Name: pre_commit-rs
Version: 0.0.0
Summary: A framework for managing and maintaining multi-language pre-commit hooks.
Home-page: https://github.com/pre-commit/pre-commit-rs
Author: Anthony Sottile
Author-email: asottile@umich.edu
License: MIT
Classifier: License :: OSI Approved :: MIT License
Classifier: Programming Language :: Python :: 3
Classifier: Programming Language :: Python :: 3 :: Only
Classifier: Programming Language :: Python :: Implementation :: CPython
Requires-Python: >=3.9
License-File: LICENSE
License-File: licenses/asottile_cfgv
License-File: licenses/pre-commit_pre-commit
